maokai/__init__.py
maokai/api/riot.py
maokai/db/__init__.py
maokai/db/common.py
maokai/db/models/league.py
maokai/db/models/match.py
maokai/db/models/summoner.py
maokai/db/models/timeline.py
maokai/db/models/views.py
maokai/db/store.py
maokai-0.1.0.dist-info/WHEEL
maokai-0.1.0.dist-info/METADATA
maokai-0.1.0.dist-info/RECORD
