Metadata-Version: 2.1
Name: maokai
Version: 0.1.0
Summary: wrapper for riot api and store it in sql database
Author: Moch Rene
Author-email: moch.rene@googlemail.com
Requires-Python: >=3.8,<4.0
Classifier: Programming Language :: Python :: 3
Classifier: Programming Language :: Python :: 3.8
Classifier: Programming Language :: Python :: 3.9
Requires-Dist: SQLAlchemy (>=1.3.23,<2.0.0)
Requires-Dist: pandas (>=1.2.3,<2.0.0)
Requires-Dist: requests (>=2.25.1,<3.0.0)
